odoo/addons/l10n_es_aeat_mod303_print_copy/README.rst
odoo/addons/l10n_es_aeat_mod303_print_copy/__init__.py
odoo/addons/l10n_es_aeat_mod303_print_copy/__manifest__.py
odoo/addons/l10n_es_aeat_mod303_print_copy/i18n/es.po
odoo/addons/l10n_es_aeat_mod303_print_copy/report/aeat_mod303.xml
odoo/addons/l10n_es_aeat_mod303_print_copy/report/report_views.xml
odoo/addons/l10n_es_aeat_mod303_print_copy/static/description/icon.png
odoo_addon_l10n_es_aeat_mod303_print_copy-15.0.2.0.0.3.dist-info/METADATA
odoo_addon_l10n_es_aeat_mod303_print_copy-15.0.2.0.0.3.dist-info/WHEEL
odoo_addon_l10n_es_aeat_mod303_print_copy-15.0.2.0.0.3.dist-info/top_level.txt
odoo_addon_l10n_es_aeat_mod303_print_copy-15.0.2.0.0.3.dist-info/RECORD
