Metadata-Version: 2.1
Name: odoo-addon-l10n_es_aeat_mod303_print_copy
Version: 15.0.2.0.0.3
Requires-Python: >=3.8
Requires-Dist: odoo-addon-l10n_es_aeat_mod303>=15.0dev,<15.1dev
Requires-Dist: odoo>=15.0a,<15.1dev
Summary: PDF del model 303
Home-page: https://github.com/sygel-technology/sy-l10n-spain
License: AGPL-3
Author: Sygel, Odoo Community Association (OCA)
Author-email: support@odoo-community.org
Classifier: Programming Language :: Python
Classifier: Framework :: Odoo
Classifier: Framework :: Odoo :: 15.0
Classifier: License :: OSI Approved :: GNU Affero General Public License v3
